kohler/__init__.py
kohler/kohler.py
kohler-0.0.6.dist-info/LICENSE
kohler-0.0.6.dist-info/METADATA
kohler-0.0.6.dist-info/WHEEL
kohler-0.0.6.dist-info/top_level.txt
kohler-0.0.6.dist-info/RECORD
