Metadata-Version: 2.1
Name: kohler
Version: 0.0.6
Summary: Python library for talking to Kohler devices
Home-page: https://github.com/niemyjski/kohler-python
Author: Blake Niemyjski
Author-email: bniemyjski@gmail.com
License: Apache
License-File: LICENSE
Requires-Dist: requests
